nilmtk/__init__.py
nilmtk/api.py
nilmtk/appliance.py
nilmtk/building.py
nilmtk/consts.py
nilmtk/dataset.py
nilmtk/dataset_converters/__init__.py
nilmtk/dataset_converters/ampds/__init__.py
nilmtk/dataset_converters/ampds/convert_ampds.py
nilmtk/dataset_converters/ampds/metadata/__init__.py
nilmtk/dataset_converters/ampds/metadata/building1.yaml
nilmtk/dataset_converters/ampds/metadata/dataset.yaml
nilmtk/dataset_converters/ampds/metadata/meter_devices.yaml
nilmtk/dataset_converters/caxe/__init__.py
nilmtk/dataset_converters/caxe/convert_caxe.py
nilmtk/dataset_converters/caxe/metadata/__init__.py
nilmtk/dataset_converters/caxe/metadata/building1.yaml
nilmtk/dataset_converters/caxe/metadata/dataset.yaml
nilmtk/dataset_converters/caxe/metadata/meter_devices.yaml
nilmtk/dataset_converters/combed/__init__.py
nilmtk/dataset_converters/combed/convert_combed.py
nilmtk/dataset_converters/combed/download.py
nilmtk/dataset_converters/combed/metadata/__init__.py
nilmtk/dataset_converters/combed/metadata/building1.yaml
nilmtk/dataset_converters/combed/metadata/building2.yaml
nilmtk/dataset_converters/combed/metadata/dataset.yaml
nilmtk/dataset_converters/combed/metadata/meter_devices.yaml
nilmtk/dataset_converters/dataport/__init__.py
nilmtk/dataset_converters/dataport/csv_converter.py
nilmtk/dataset_converters/dataport/download_dataport.py
nilmtk/dataset_converters/dataport/metadata/__init__.py
nilmtk/dataset_converters/dataport/metadata/dataset.yaml
nilmtk/dataset_converters/dataport/metadata/meter_devices.yaml
nilmtk/dataset_converters/deddiag/__init__.py
nilmtk/dataset_converters/deddiag/convert_deddiag.py
nilmtk/dataset_converters/deddiag/metadata/__init__.py
nilmtk/dataset_converters/deddiag/metadata/building8.yaml
nilmtk/dataset_converters/deddiag/metadata/dataset.yaml
nilmtk/dataset_converters/deddiag/metadata/meter_devices.yaml
nilmtk/dataset_converters/deddiag/readme.md
nilmtk/dataset_converters/dred/Readme.md
nilmtk/dataset_converters/dred/__init__.py
nilmtk_s14pe-0.4.0.dev2.dist-info/LICENSE
nilmtk_s14pe-0.4.0.dev2.dist-info/METADATA
nilmtk_s14pe-0.4.0.dev2.dist-info/WHEEL
nilmtk_s14pe-0.4.0.dev2.dist-info/RECORD
