Metadata-Version: 2.1
Name: nilmtk_s14pe
Version: 0.4.0.dev2
Summary: 
Author: FelixS
Author-email: fsievers93@gmail.com
Requires-Python: >=3.11,<3.12
Classifier: Programming Language :: Python :: 3
Classifier: Programming Language :: Python :: 3.11
Requires-Dist: hmmlearn (>=0.3.3,<0.4.0)
Requires-Dist: ipython (>=8.29.0,<9.0.0)
Requires-Dist: matplotlib (>=3.9.2,<4.0.0)
Requires-Dist: networkx (>=3.4.2,<4.0.0)
Requires-Dist: nilm_metadata_s14pe (==0.2.5.dev5)
Requires-Dist: pandas (>=2.2.3,<3.0.0)
Requires-Dist: scikit-learn (>=1.5.2,<2.0.0)
Requires-Dist: scipy (>=1.14.1,<2.0.0)
Requires-Dist: tables (>=3.10.1,<4.0.0)
